PyPSP/PyPSP.py
PyPSP/__init__.py
pypsp-1.0.1.dist-info/METADATA
pypsp-1.0.1.dist-info/WHEEL
pypsp-1.0.1.dist-info/licenses/LICENSE
pypsp-1.0.1.dist-info/RECORD
